bitglitter/__init__.py
bitglitter/__main__.py
bitglitter/cli/analyzer.py
bitglitter/cli/args.py
bitglitter/config/config.py
bitglitter/config/configfunctions.py
bitglitter/config/configobjects.py
bitglitter/config/constants.py
bitglitter/config/loggingset.py
bitglitter/filepackager/fileio.py
bitglitter/filepackager/filepackager.py
bitglitter/palettes/palettefunctions.py
bitglitter/palettes/paletteobjects.py
bitglitter/palettes/paletteutilities.py
bitglitter/protocols/protocolhandler.py
bitglitter/protocols/protocolobjects.py
bitglitter/protocols/protocolversions.py
bitglitter/protocols/protocol_one/read/protocol_one_postprocess.py
bitglitter/protocols/protocol_one/read/protocol_one_postprocessobjects.py
bitglitter/protocols/protocol_one/write/protocol_one_preprocess.py
bitglitter/protocols/protocol_one/write/protocol_one_preprocessobjects.py
bitglitter/protocols/protocol_one/write/protocol_one_renderassets.py
bitglitter/protocols/protocol_one/write/protocol_one_renderlogic.py
bitglitter/protocols/protocol_one/write/protocol_one_renderloop.py
bitglitter/protocols/protocol_one/write/protocol_one_verifywriteparameters.py
bitglitter/read/assembler.py
bitglitter/read/coloranalysis.py
bitglitter/read/decoder.py
bitglitter/read/decoderassets.py
bitglitter/read/fileslicer.py
bitglitter/read/framehandler.py
bitglitter/read/framelockon.py
bitglitter/read/partialsave.py
bitglitter/read/partialsaveassets.py
bitglitter/read/read.py
bitglitter/read/savedfilefunctions.py
bitglitter/read/verifyreadparameters.py
bitglitter/read/videoframepuller.py
bitglitter/tests/test_coloranalysis.py
bitglitter/tests/test_paletteutilites.py
bitglitter/utilities/filemanipulation.py
bitglitter/utilities/generalverifyfunctions.py
bitglitter/utilities/gui_utilities.py
bitglitter/write/renderhandler.py
bitglitter/write/rendervideo.py
bitglitter/write/write.py
BitGlitter-1.0.3.dist-info/LICENSE
BitGlitter-1.0.3.dist-info/METADATA
BitGlitter-1.0.3.dist-info/WHEEL
BitGlitter-1.0.3.dist-info/entry_points.txt
BitGlitter-1.0.3.dist-info/top_level.txt
BitGlitter-1.0.3.dist-info/RECORD
