Metadata-Version: 2.1
Name: BitGlitter
Version: 1.0.3
Summary: ⚡ Embed data payloads inside of ordinary images or video, through high performance 2-D matrix codes.
Home-page: https://github.com/MarkMichon1/BitGlitter
Author: Mark Michon
Author-email: markmichon7@gmail.com
License: UNKNOWN
Platform: UNKNOWN
Classifier: Programming Language :: Python :: 3.7
Classifier: License :: OSI Approved :: MIT License
Classifier: Operating System :: OS Independent
Requires-Dist: bitstring
Requires-Dist: cryptography
Requires-Dist: ffmpeg-python
Requires-Dist: opencv-python
Requires-Dist: Pillow
Requires-Dist: argparse
